data/crowd/ratings.jsonl
data/crowd/ratings.jsonl.gz
data/crowd/responses.jsonl
data/crowd/responses.jsonl.gz
data/crowd/study1_retrieval.jsonl.gz
data/figures/.gitkeep
data/figures/figure-axioms-mutual-consistency-pre.pdf
data/figures/figure-axioms-mutual-consistency.pdf
data/figures/figure-vote-axiom-decisiveness-consistency.pdf
data/figures/figure-vote-axiom-judgment-consistency.pdf
docs/axiom-development.md
docs/axioms.md
docs/migration-v1.md
docs/rag-axioms.md
docs/term_frequency.py.diff
experiments/.gitignore
experiments/ictir2025.ipynb
experiments/llm_ratings.py
experiments/llm_responses.py
experiments/pyterrier_kwiksort.ipynb
experiments/pyterrier_kwiksort_learned.ipynb
experiments/pyterrier_ltr_features.ipynb
experiments/pyterrier_post_hoc_analysis_of_runs_and_qrels.ipynb
experiments/pyterrier_preferences.ipynb
experiments/pyterrier_preferences_parallel.ipynb
experiments/pyterrier_reranking_comparison.ipynb
experiments/ray-env.yml
experiments/sigir2022_showcase.ipynb
experiments/sigir2022/evaluations-paper.ipynb
experiments/sigir2022/grid-search-axiomatic-re-ranking-approaches.ipynb
experiments/sigir2022/table-axiom-distribution-on-trec-dl.ipynb
experiments/sigir2022/trec-dl-ms-marco-passage.ipynb
ir_axioms/__init__.py
ir_axioms/__main__.py
ir_axioms/cli.py
ir_axioms/dependency_injection.py
ir_axioms/logging.py
ir_axioms/py.typed
ir_axioms/algorithms/__init__.py
ir_axioms/algorithms/ranking.py
ir_axioms/axiom/__init__.py
ir_axioms/axiom/arithmetic.py
ir_axioms/axiom/base.py
ir_axioms/axiom/cache.py
ir_axioms/axiom/estimator.py
ir_axioms/axiom/parallel.py
ir_axioms/axiom/precondition.py
ir_axioms/axiom/simple.py
ir_axioms/axiom/utils.py
ir_axioms/axiom/generation/__init__.py
ir_axioms/axiom/generation/clarity.py
ir_axioms/axiom/generation/coherence.py
ir_axioms/axiom/generation/consistency.py
ir_axioms/axiom/generation/correctness.py
ir_axioms/axiom/generation/coverage.py
ir_axioms/axiom/generation/crowd.py
ir_axioms/axiom/generation/llm.py
ir_axioms-1.1.dist-info/licenses/LICENSE
ir_axioms-1.1.dist-info/METADATA
ir_axioms-1.1.dist-info/WHEEL
ir_axioms-1.1.dist-info/entry_points.txt
ir_axioms-1.1.dist-info/top_level.txt
ir_axioms-1.1.dist-info/RECORD
