Metadata-Version: 2.4
Name: ir_axioms
Version: 1.1
Summary: Axiomatic constraints for information retrieval and retrieval-augmented generation.
Author-email: Jan Heinrich Merker <heinrich.merker@uni-jena.de>, Alexander Bondarenko <alexander.bondarenko@uni-jena.de>, Maik Fröbe <maik.froebe@uni-jena.de>, Benno Stein <benno.stein@uni-weimar.de>, Michael Völske <michael.voelske@uni-weimar.de>, Matthias Hagen <matthias.hagen@uni-jena.de>, Martin Potthast <martin.potthast@uni-kassel.de>
Project-URL: Homepage, https://github.com/webis-de/ir_axioms
Project-URL: Bug Tracker, https://github.com/webis-de/ir_axioms/issues
Classifier: Programming Language :: Python :: 3
Classifier: Programming Language :: Python :: 3 :: Only
Classifier: Programming Language :: Python :: 3.11
Classifier: Programming Language :: Python :: 3.12
Classifier: Operating System :: OS Independent
Classifier: Intended Audience :: Science/Research
Classifier: Topic :: Scientific/Engineering
Requires-Python: >=3.11
License-File: LICENSE
Requires-Dist: annotated-types~=0.7.0
Requires-Dist: cached-property~=2.0
Requires-Dist: cyclopts~=3.0
Requires-Dist: fasttext~=0.9.3
Requires-Dist: frozendict~=2.4
Requires-Dist: huggingface-hub[hf_xet]<0.35.0,>=0.30.1
Requires-Dist: injector~=0.22.0
Requires-Dist: ir-datasets~=0.5.9
Requires-Dist: joblib~=1.4
Requires-Dist: language-tool-python~=2.8
Requires-Dist: more-itertools~=10.5
Requires-Dist: negspacy~=1.0
Requires-Dist: nltk~=3.9
Requires-Dist: numpy~=1.26
Requires-Dist: pandas~=2.2
Requires-Dist: python-dotenv~=1.0
Requires-Dist: rouge-score~=0.1.2
Requires-Dist: scikit-learn~=1.4
Requires-Dist: spacy~=3.7
Requires-Dist: targer-api~=1.1
Requires-Dist: textacy~=0.13.0
Requires-Dist: tqdm~=4.67
Requires-Dist: trectools~=0.0.49
Provides-Extra: tests
Requires-Dist: bandit[toml]~=1.8; extra == "tests"
Requires-Dist: mypy~=1.13; extra == "tests"
Requires-Dist: pytest~=8.3; extra == "tests"
Requires-Dist: pytest-cov~=6.0; extra == "tests"
Requires-Dist: ruff~=0.12.7; extra == "tests"
Requires-Dist: types-tqdm~=4.66; extra == "tests"
Provides-Extra: experiments
Requires-Dist: cappr[hf]~=0.9.6; extra == "experiments"
Requires-Dist: ir-measures~=0.3.6; extra == "experiments"
Requires-Dist: jupyter~=1.1; extra == "experiments"
Requires-Dist: lightgbm~=4.5; extra == "experiments"
Requires-Dist: ragas~=0.3.0; extra == "experiments"
Requires-Dist: ray[data,default]~=2.48; extra == "experiments"
Requires-Dist: seaborn~=0.13.2; extra == "experiments"
Requires-Dist: transformers~=4.48; extra == "experiments"
Requires-Dist: typing-extensions~=4.12; extra == "experiments"
Requires-Dist: xgboost<4.0,>=2.1; extra == "experiments"
Provides-Extra: pyserini
Requires-Dist: pyserini<2.0,>=0.43; extra == "pyserini"
Provides-Extra: pyterrier
Requires-Dist: python-terrier~=0.13.0; extra == "pyterrier"
Provides-Extra: keybert
Requires-Dist: keybert<0.10.0,>=0.8.5; extra == "keybert"
Provides-Extra: sbert
Requires-Dist: sentence-transformers<6.0,>=4.0; extra == "sbert"
Dynamic: license-file
